aiodnsbl/__init__.py
aiodnsbl/checker.py
aiodnsbl/providers.py
aiodnsbl-1.0.0.dist-info/LICENSE
aiodnsbl-1.0.0.dist-info/METADATA
aiodnsbl-1.0.0.dist-info/WHEEL
aiodnsbl-1.0.0.dist-info/RECORD
