Metadata-Version: 2.1
Name: aiodnsbl
Version: 1.0.0
Summary: Async DNSBL lists checker
Home-page: https://github.com/ninoseki/aiodnsbl
License: MIT
Author: Manabu Niseki
Author-email: manabu.niseki@gmail.com
Requires-Python: >=3.8.1,<4.0.0
Classifier: License :: OSI Approved :: MIT License
Classifier: Programming Language :: Python :: 3
Classifier: Programming Language :: Python :: 3.9
Classifier: Programming Language :: Python :: 3.10
Classifier: Programming Language :: Python :: 3.11
Requires-Dist: aiodns (>=3.0,<4.0)
Requires-Dist: idna (>=3.4,<4.0)
Project-URL: Repository, https://github.com/ninoseki/aiodnsbl
